setup.cfg
setup.py
mlmmj_archiver/__init__.py
mlmmj_archiver/main.py
mlmmj_archiver.egg-info/PKG-INFO
mlmmj_archiver.egg-info/SOURCES.txt
mlmmj_archiver.egg-info/dependency_links.txt
mlmmj_archiver.egg-info/entry_points.txt
mlmmj_archiver.egg-info/not-zip-safe
mlmmj_archiver.egg-info/requires.txt
mlmmj_archiver.egg-info/top_level.txt