Metadata-Version: 1.0
Name: mlmmj_archiver
Version: 0.1dev
Summary: Wrapper script for Hypermail to manage the archives of mlmmj lists.
Home-page: http://packages.python.org/mlmmj_archiver
Author: Mate Gabri
Author-email: mate@gabri.hu
License: BSD
Keywords: mlmmj archive hypermail
Platform: UNKNOWN
Classifier: Development Status :: 4 - Beta
Classifier: License :: OSI Approved :: BSD License
Classifier: Topic :: System :: Archiving
Classifier: Topic :: Utilities
